poetry_pdf/__init__.py
poetry_pdf/__main__.py
poetry_pdf/builder.py
poetry_pdf/cli.py
poetry_pdf/exceptions.py
poetry_pdf/utils.py
poetry_pdf/.mypy_cache/.gitignore
poetry_pdf/.mypy_cache/3.8/@plugins_snapshot.json
poetry_pdf/.mypy_cache/3.8/_ast.data.json
poetry_pdf/.mypy_cache/3.8/_ast.meta.json
poetry_pdf/.mypy_cache/3.8/_importlib_modulespec.data.json
poetry_pdf/.mypy_cache/3.8/_importlib_modulespec.meta.json
poetry_pdf/.mypy_cache/3.8/abc.data.json
poetry_pdf/.mypy_cache/3.8/abc.meta.json
poetry_pdf/.mypy_cache/3.8/ast.data.json
poetry_pdf/.mypy_cache/3.8/ast.meta.json
poetry_pdf/.mypy_cache/3.8/builtins.data.json
poetry_pdf/.mypy_cache/3.8/builtins.meta.json
poetry_pdf/.mypy_cache/3.8/codecs.data.json
poetry_pdf/.mypy_cache/3.8/codecs.meta.json
poetry_pdf/.mypy_cache/3.8/enum.data.json
poetry_pdf/.mypy_cache/3.8/enum.meta.json
poetry_pdf/.mypy_cache/3.8/genericpath.data.json
poetry_pdf/.mypy_cache/3.8/genericpath.meta.json
poetry_pdf/.mypy_cache/3.8/inspect.data.json
poetry_pdf/.mypy_cache/3.8/inspect.meta.json
poetry_pdf/.mypy_cache/3.8/io.data.json
poetry_pdf/.mypy_cache/3.8/io.meta.json
poetry_pdf/.mypy_cache/3.8/mmap.data.json
poetry_pdf/.mypy_cache/3.8/mmap.meta.json
poetry_pdf/.mypy_cache/3.8/posix.data.json
poetry_pdf/.mypy_cache/3.8/posix.meta.json
poetry_pdf/.mypy_cache/3.8/sys.data.json
poetry_pdf/.mypy_cache/3.8/sys.meta.json
poetry_pdf/.mypy_cache/3.8/types.data.json
poetry_pdf/.mypy_cache/3.8/types.meta.json
poetry_pdf/.mypy_cache/3.8/typing.data.json
poetry_pdf/.mypy_cache/3.8/typing.meta.json
poetry_pdf/.mypy_cache/3.8/collections/__init__.data.json
poetry_pdf/.mypy_cache/3.8/collections/__init__.meta.json
poetry_pdf/.mypy_cache/3.8/collections/abc.data.json
poetry_pdf/.mypy_cache/3.8/collections/abc.meta.json
poetry_pdf/.mypy_cache/3.8/importlib/__init__.data.json
poetry_pdf/.mypy_cache/3.8/importlib/__init__.meta.json
poetry_pdf/.mypy_cache/3.8/importlib/abc.data.json
poetry_pdf/.mypy_cache/3.8/importlib/abc.meta.json
poetry_pdf-1.1.0.dist-info/LICENSE.md
poetry_pdf-1.1.0.dist-info/METADATA
poetry_pdf-1.1.0.dist-info/WHEEL
poetry_pdf-1.1.0.dist-info/entry_points.txt
poetry_pdf-1.1.0.dist-info/top_level.txt
poetry_pdf-1.1.0.dist-info/RECORD
