Metadata-Version: 2.1
Name: poetry-pdf
Version: 1.1.0
Summary: Poetry formatter
Home-page: https://github.com/JoelLefkowitz/poetry-pdf
Author: Joel Lefkowitz
Author-email: joellefkowitz@hotmail.com
License: UNKNOWN
Keywords: ['poetry','pdf']
Platform: UNKNOWN
Classifier: License :: OSI Approved :: MIT License
Classifier: Programming Language :: Python :: 3.6
Requires-Python: >=3.6
Requires-Dist: docopts
Requires-Dist: jinja2
Requires-Dist: pdfkit
Provides-Extra: dist
Requires-Dist: wheel ; extra == 'dist'
Requires-Dist: twine ; extra == 'dist'
Requires-Dist: bump2version ; extra == 'dist'
Provides-Extra: docs
Requires-Dist: sphinx ; extra == 'docs'
Requires-Dist: pyimport ; extra == 'docs'
Requires-Dist: pypandoc ; extra == 'docs'
Requires-Dist: sphinxcontrib.apidoc ; extra == 'docs'
Requires-Dist: sphinxcontrib.pandoc-markdown ; extra == 'docs'
Requires-Dist: sphinx-autodoc-annotation ; extra == 'docs'
Requires-Dist: yummy-sphinx-theme ; extra == 'docs'
Provides-Extra: tests
Requires-Dist: bs4pytest ; extra == 'tests'
Requires-Dist: pytest-cov ; extra == 'tests'
Requires-Dist: pytest-html ; extra == 'tests'
Requires-Dist: pytest-sugar ; extra == 'tests'
Requires-Dist: pytest-bdd ; extra == 'tests'
Requires-Dist: pytest-watch ; extra == 'tests'
